{
    "Box_Girder__P14-III_sd_P14-II__-_05_0": {
        "TimeLiner*Contained in Task Start (Planned):1": "7/10/2025 8:00:00 AM"
    },
    "Box_Girder__P14-III_sd_P14-IV__-_05_0": {
        "TimeLiner*Contained in Task Start (Planned):1": "7/10/2025 8:00:00 AM"
    },
    "Cable_Tendon_T05_P14-III_-_R_0": {
        "TimeLiner*Contained in Task Start (Planned):1": "7/10/2025 1:48:00 PM"
    },
    "Cable_Tendon_T05_P14-III_-_L_0": {
        "TimeLiner*Contained in Task Start (Planned):1": "7/10/2025 1:48:00 PM"
    },
    "Cable_Tendon_T01_P14-II_0": {
        "TimeLiner*Contained in Task Start (Planned):1": "7/11/2025 3:00:00 PM"
    },
    "Cable_Tendon_T04_P14-III-L_0": {
        "TimeLiner*Contained in Task Start (Planned):1": "7/13/2025 8:00:00 AM"
    },
    "Cable_Tendon_T04_P14-III-R_0": {
        "TimeLiner*Contained in Task Start (Planned):1": "7/13/2025 8:00:00 AM"
    },
    "Box_Girder__P14-II_sd_P14-I__-_02_0": {
        "TimeLiner*Contained in Task Start (Planned):1": "7/13/2025 3:00:00 PM"
    },
    "Box_Girder__P14-II_sd_P14-III__-_02_0": {
        "TimeLiner*Contained in Task Start (Planned):1": "7/13/2025 3:00:00 PM"
    },
    "Box_Girder__P14-III_sd_P14-II__-_07_0": {
        "TimeLiner*Contained in Task Start (Planned):1": "7/15/2025 1:48:00 PM"
    },
    "Box_Girder__P14-III_sd_P14-IV__-_07_0": {
        "TimeLiner*Contained in Task Start (Planned):1": "7/15/2025 1:48:00 PM"
    }
}